{"map": {"type": "FeatureCollection", "features": [{"geometry": {"type": "MultiLineString", "coordinates": [[[-105.496438, 39.95463021], [-105.496322, 39.95426162], [-105.49629, 39.9537407], [-105.496315, 39.95330638], [-105.496424, 39.95278485], [-105.496725, 39.95246377], [-105.496888, 39.95237196], [-105.496951, 39.95227745], [-105.496888, 39.95212], [-105.496471, 39.95143858], [-105.496412, 39.95100462]]]}, "type": "Feature"}], "bbox": [-105.496951, 39.95100462, -105.49629, 39.95463021]}, "area_id": "1474", "description": "<p>Doubletrack connection to the neighborhood. \u00a0Snakes through some pretty woods at a steady climb (if you start in the neighborhood), but since it doesn't really connect to other trails, BMA considers this a neighborhood access trail ... good to know about if you have a mechanical and need to get back to Nederland.</p>", "elevation_gain": 42.367200000000004, "cool_rating": 1.0, "difficulty_rating": 2, "tech_rating": 1.0, "id": "1754", "doc_type": "trail", "name": "Big Springs", "length": 402.335, "aerobic_rating": 1.5, "image_url": "http://bouldermountainbike.org/sites/default/files/imagecache/710x230/101_2437-1.JPG", "trailheads": {"type": "FeatureCollection", "features": [{"geometry": {"type": "Point", "coordinates": [-105.496438, 39.95463021]}, "type": "Feature"}]}}